README.md
setup.py
pyexpr/__init__.py
pyexpr/exprast.py
pyexpr/lex.py
pyexpr/parser.py
pyexpr.egg-info/PKG-INFO
pyexpr.egg-info/SOURCES.txt
pyexpr.egg-info/dependency_links.txt
pyexpr.egg-info/top_level.txt