Metadata-Version: 1.0
Name: pyexpr
Version: 0.0.3.1
Summary: A python expression ecaluator
Home-page: https://github.com/lennon-guan/pyexpr
Author: UNKNOWN
Author-email: UNKNOWN
License: UNKNOWN
Platform: UNKNOWN
